HDL/si.v
// Generate sum outputs (S)
// S_i = P_i XOR C_i
// This matches si.cir in SPICE
module si (
    input  wire [4:0] p,        // Propagate signals
    input  wire [4:0] c,        // Carry signals (c[0]=cin, c[1]=c1, c[2]=c2, c[3]=c3, c[4]=c4)
    output wire [4:0] s         // Sum outputs
);
    // Sum: S_i = P_i XOR C_i
    assign s[0] = p[0] ^ c[0];
    assign s[1] = p[1] ^ c[1];
    assign s[2] = p[2] ^ c[2];
    assign s[3] = p[3] ^ c[3];
    assign s[4] = p[4] ^ c[4];
endmodule

HDL/carry.v
// Carry Lookahead Logic for 5-bit CLA
// Uses inverted generates (G_bar) and produces carries using NAND-based logic
// This matches carry.cir in SPICE which uses NAND gates
module carry (
    input  wire [4:0] p,        // Propagate signals
    input  wire [4:0] g_bar,    // Generate signals (inverted)
    input  wire       c0,       // Carry input (Cin)
    output wire [4:0] c,        // Carry outputs c1, c2, c3, c4, cout
    output wire       cout
);

    // Internal signals for NAND-based implementation
    wire [4:0] g;               // Non-inverted generates
    wire       c1_inv;
    wire       c2_nand, c3_nand1, c3_nand2;
    wire       c4_nand1, c4_nand2, c4_nand3;
    wire       c5_nand1, c5_nand2, c5_nand3, c5_nand4;

    // Convert G_bar to G using inverters
    assign g[0] = ~g_bar[0];
    assign g[1] = ~g_bar[1];
    assign g[2] = ~g_bar[2];
    assign g[3] = ~g_bar[3];
    assign g[4] = ~g_bar[4];

    // C1 = G0 + P0·C0
    // Using: C1 = ~(~G0 & ~(P0·C0))
    assign c1_inv = ~(p[0] & c0);
    assign c[0] = ~(g_bar[0] & c1_inv);

    // C2 = G1 + P1·G0 + P1·P0·C0
    // Using NAND gates:
    assign c2_nand = ~(p[1] & g[0]);
    assign c[1] = ~(g_bar[1] & c2_nand & c1_inv);

    // C3 = G2 + P2·G1 + P2·P1·G0 + P2·P1·P0·C0
    // Using NAND gates:
    assign c3_nand1 = ~(p[2] & g[1]);
    assign c3_nand2 = ~(p[2] & p[1] & g[0]);
    assign c[2] = ~(g_bar[2] & c3_nand1 & c3_nand2 & c1_inv);

    // C4 = G3 + P3·G2 + P3·P2·G1 + P3·P2·P1·G0 + P3·P2·P1·P0·C0
    // Using NAND gates:
    assign c4_nand1 = ~(p[3] & g[2]);
    assign c4_nand2 = ~(p[3] & p[2] & g[1]);
    assign c4_nand3 = ~(p[3] & p[2] & p[1] & g[0]);
    assign c[3] = ~(g_bar[3] & c4_nand1 & c4_nand2 & c4_nand3 & c1_inv);

    // C5 (Cout) = G4 + P4·G3 + P4·P3·G2 + P4·P3·P2·G1 + P4·P3·P2·P1·G0 + P4·P3·P2·P1·P0·C0
    // Using NAND gates:
    assign c5_nand1 = ~(p[4] & g[3]);
    assign c5_nand2 = ~(p[4] & p[3] & g[2]);
    assign c5_nand3 = ~(p[4] & p[3] & p[2] & g[1]);
    assign c5_nand4 = ~(p[4] & p[3] & p[2] & p[1] & g[0]);
    assign cout = ~(g_bar[4] & c5_nand1 & c5_nand2 & c5_nand3 & c5_nand4 & c1_inv);

    assign c[4] = cout;

endmodule

HDL/pi.v
// Propagate for 5-bit CLA (using XOR)
// P_i = A_i XOR B_i
// This matches pi.cir in SPICE
module pi (
    input  wire [4:0] a,
    input  wire [4:0] b,
    output wire [4:0] p
);
    // P_i = A_i XOR B_i
    assign p[0] = a[0] ^ b[0];
    assign p[1] = a[1] ^ b[1];
    assign p[2] = a[2] ^ b[2];
    assign p[3] = a[3] ^ b[3];
    assign p[4] = a[4] ^ b[4];
endmodule

HDL/gi.v
// Generate inverted carry generate signals (G_bar)
// G_bar_i = NAND(A_i, B_i)
// This matches gi_bar.cir in SPICE
module gi (
    input  wire [4:0] a,
    input  wire [4:0] b,
    output wire [4:0] g_bar
);
    // G_bar_i = ~(A_i & B_i) = NAND(A_i, B_i)
    assign g_bar[0] = ~(a[0] & b[0]);
    assign g_bar[1] = ~(a[1] & b[1]);
    assign g_bar[2] = ~(a[2] & b[2]);
    assign g_bar[3] = ~(a[3] & b[3]);
    assign g_bar[4] = ~(a[4] & b[4]);
endmodule

HDL/cla_5bit.v
// 5-bit Carry Lookahead Adder - Top Module
// Gate-level implementation matching CMOS-static-2 SPICE design
module cla_5bit (
    input  wire [4:0] a,        // 5-bit input A
    input  wire [4:0] b,        // 5-bit input B
    input  wire       cin,      // Carry input
    output wire [4:0] sum,      // 5-bit sum output
    output wire       cout      // Carry output
);

    // Internal signals
    wire [4:0] p;               // Propagate signals
    wire [4:0] g_bar;           // Generate signals (inverted)
    wire [4:0] c_internal;      // Internal carries
    wire [4:0] c_for_sum;       // Carries for sum calculation

    // Instantiate Generate (inverted) logic
    gi gi_inst (
        .a(a),
        .b(b),
        .g_bar(g_bar)
    );

    // Instantiate Propagate logic
    pi pi_inst (
        .a(a),
        .b(b),
        .p(p)
    );

    // Instantiate Carry Lookahead Unit
    carry carry_inst (
        .p(p),
        .g_bar(g_bar),
        .c0(cin),
        .c(c_internal),
        .cout(cout)
    );

    // Prepare carries for sum calculation: c_for_sum = {c4, c3, c2, c1, cin}
    assign c_for_sum = {c_internal[3:0], cin};

    // Instantiate Sum Logic
    si si_inst (
        .p(p),
        .c(c_for_sum),
        .s(sum)
    );

endmodule

HDL/t_cla.v
`timescale 1ns/1ps

module t_cla;
    reg  [4:0] a;
    reg  [4:0] b;
    reg        cin;
    wire [4:0] sum;
    wire       cout;

    // Instantiate the DUT (Device Under Test)
    cla_5bit dut (
        .a(a),
        .b(b),
        .cin(cin),
        .sum(sum),
        .cout(cout)
    );

    // Expected result - separated for GTKWave
    reg [5:0] expected;
    reg [5:0] calculated;
    reg [4:0] expected_sum;   // Separate expected sum for waveform
    reg       expected_cout;   // Separate expected cout for waveform
    integer errors;
    integer test_num;
    integer i, j;

    // Generate waveform dump - MUST BE FIRST
    initial begin
        $dumpfile("cla_5bit.vcd");
        $dumpvars(0, t_cla);
    end

    initial begin
        $display("================================================================");
        $display("  5-BIT CARRY LOOKAHEAD ADDER - EXHAUSTIVE TEST SUITE");
        $display("  Testing ALL combinations with Cin=0: 32 x 32 = 1024 tests");
        $display("  Gate-Level Verilog (matching CMOS-static-2 SPICE)");
        $display("================================================================");
        $display("");

        errors = 0;
        test_num = 0;

        // Initialize - Cin is always 0
        cin = 1'b0;
        expected_sum = 5'b00000;
        expected_cout = 1'b0;

        $display("Starting exhaustive testing with Cin = 0...");
        $display("");

        // Loop through all combinations of A (0 to 31)
        for (i = 0; i < 32; i = i + 1) begin
            // Loop through all combinations of B (0 to 31)
            for (j = 0; j < 32; j = j + 1) begin
                test_num = test_num + 1;
                
                // Set inputs
                a = i[4:0];
                b = j[4:0];
                
                // Calculate expected result (A + B + 0)
                calculated = a + b;
                expected = calculated;
                expected_sum = expected[4:0];
                expected_cout = expected[5];
                
                // Wait for circuit propagation
                #10;
                
                // Check result
                if ({cout, sum} !== expected) begin
                    $display("================================================================");
                    $display("TEST %0d FAILED!", test_num);
                    $display("================================================================");
                    $display("  Inputs:");
                    $display("    A     = %b (%2d decimal)", a, a);
                    $display("    B     = %b (%2d decimal)", b, b);
                    $display("    Cin   = %b (always 0)", cin);
                    $display("  Expected:");
                    $display("    Sum   = %b (%2d decimal)", expected_sum, expected_sum);
                    $display("    Cout  = %b", expected_cout);
                    $display("    Total = %2d (6-bit: %b)", expected, expected);
                    $display("  Got:");
                    $display("    Sum   = %b (%2d decimal)", sum, sum);
                    $display("    Cout  = %b", cout);
                    $display("    Total = %2d (6-bit: %b)", {cout, sum}, {cout, sum});
                    $display("================================================================");
                    $display("");
                    errors = errors + 1;
                end
                
                // Print progress every 128 tests (more frequent for 1024 total)
                if (test_num % 128 == 0) begin
                    $display("Progress: %4d/1024 tests completed (%3d%%)...", 
                             test_num, (test_num * 100) / 1024);
                end
            end
        end

        // Summary
        $display("");
        $display("================================================================");
        $display("  VERIFICATION SUMMARY");
        $display("================================================================");
        $display("Test configuration: Cin = 0 (fixed)");
        $display("Total tests run:    %0d", test_num);
        $display("Tests passed:       %0d", test_num - errors);
        $display("Tests failed:       %0d", errors);
        $display("Pass rate:          %0d%%", ((test_num - errors) * 100) / test_num);
        $display("================================================================");
        
        if (errors == 0) begin
            $display("");
            $display("    ****************************************************");
            $display("    ***  SUCCESS! ALL %0d TESTS PASSED!  ***", test_num);
            $display("    ****************************************************");
            $display("");
        end else begin
            $display("");
            $display("    ****************************************************");
            $display("    ***  FAILURE! %0d out of %0d tests FAILED  ***", errors, test_num);
            $display("    ****************************************************");
            $display("");
        end
        
        $display("================================================================");
        $display("");
        $display("Waveform file: cla_5bit.vcd");
        $display("View with:     gtkwave cla_5bit.vcd");
        $display("               gtkwave cla_5bit.vcd cla_5bit.gtkw");
        $display("");
        $display("================================================================");

        #10;
        $finish;
    end

endmodule

HDL/cla_5bit.vcd
$date
	Wed Nov 26 10:17:55 2025
$end
$version
	Icarus Verilog
$end
$timescale
	1ps
$end
$scope module t_cla $end
$var wire 5 ! sum [4:0] $end
$var wire 1 " cout $end
$var reg 5 # a [4:0] $end
$var reg 5 $ b [4:0] $end
$var reg 6 % calculated [5:0] $end
$var reg 1 & cin $end
$var reg 6 ' expected [5:0] $end
$var reg 1 ( expected_cout $end
$var reg 5 ) expected_sum [4:0] $end
$var integer 32 * errors [31:0] $end
$var integer 32 + i [31:0] $end
$var integer 32 , j [31:0] $end
$var integer 32 - test_num [31:0] $end
$scope module dut $end
$var wire 5 . a [4:0] $end
$var wire 5 / b [4:0] $end
$var wire 1 & cin $end
$var wire 5 0 sum [4:0] $end
$var wire 5 1 p [4:0] $end
$var wire 5 2 g_bar [4:0] $end
$var wire 1 " cout $end
$var wire 5 3 c_internal [4:0] $end
$var wire 5 4 c_for_sum [4:0] $end
$scope module carry_inst $end
$var wire 1 & c0 $end
$var wire 1 5 c1_inv $end
$var wire 1 6 c2_nand $end
$var wire 1 7 c3_nand1 $end
$var wire 1 8 c3_nand2 $end
$var wire 1 9 c4_nand1 $end
$var wire 1 : c4_nand2 $end
$var wire 1 ; c4_nand3 $end
$var wire 1 < c5_nand1 $end
$var wire 1 = c5_nand2 $end
$var wire 1 > c5_nand3 $end
$var wire 1 ? c5_nand4 $end
$var wire 1 " cout $end
$var wire 5 @ p [4:0] $end
$var wire 5 A g_bar [4:0] $end
$var wire 5 B g [4:0] $end
$var wire 5 C c [4:0] $end
$upscope $end
$scope module gi_inst $end
$var wire 5 D a [4:0] $end
$var wire 5 E b [4:0] $end
$var wire 5 F g_bar [4:0] $end
$upscope $end
$scope module pi_inst $end
$var wire 5 G a [4:0] $end
$var wire 5 H b [4:0] $end
$var wire 5 I p [4:0] $end
$upscope $end
$scope module si_inst $end
$var wire 5 J c [4:0] $end
$var wire 5 K p [4:0] $end
$var wire 5 L s [4:0] $end
$upscope $end
$upscope $end
$upscope $end
$enddefinitions $end
$comment Show the parameter values. $end
$dumpall
$end
#0
$dumpvars
b0 L
b0 K
b0 J
b0 I
b0 H
b0 G
b11111 F
b0 E
b0 D
b0 C
b0 B
b11111 A
b0 @
1?
1>
1=
1<
1;
1:
19
18
17
16
15
b0 4
b0 3
b11111 2
b0 1
b0 0
b0 /
b0 .
b1 -
b0 ,
b0 +
b0 *
b0 )
0(
b0 '
0&
b0 %
b0 $
b0 #
0"
b0 !
$end
#10000
b1 !
b1 0
b1 L
b1 1
b1 @
b1 I
b1 K
b1 )
b1 '
b1 %
b1 $
b1 /
b1 E
b1 H
b10 -
b1 ,
#20000
b10 !
b10 0
b10 L
b10 1
b10 @
b10 I
b10 K
b10 )
b10 '
b10 %
b10 $
b10 /
b10 E
b10 H
b11 -
b10 ,
#30000
b11 !
b11 0
b11 L
b11 1
b11 @
b11 I
b11 K
b11 )
b11 '
b11 %
b11 $
b11 /
b11 E
b11 H
b100 -
b11 ,
#40000
b100 !
b100 0
b100 L
b100 1
b100 @
b100 I
b100 K
b100 )
b100 '
b100 %
b100 $
b100 /
b100 E
b100 H
b101 -
b100 ,
#50000
b101 !
b101 0
b101 L
b101 1
b101 @
b101 I
b101 K
b101 )
b101 '
b101 %
b101 $
b101 /
b101 E
b101 H
b110 -
b101 ,
#60000
b110 !
b110 0
b110 L
b110 1
b110 @
b110 I
b110 K
b110 )
b110 '
b110 %
b110 $
b110 /
b110 E
b110 H
b111 -
b110 ,
#70000
b111 !
b111 0
b111 L
b111 1
b111 @
b111 I
b111 K
b111 )
b111 '
b111 %
b111 $
b111 /
b111 E
b111 H
b1000 -
b111 ,
#80000
b1000 !
b1000 0
b1000 L
b1000 1
b1000 @
b1000 I
b1000 K
b1000 )
b1000 '
b1000 %
b1000 $
b1000 /
b1000 E
b1000 H
b1001 -
b1000 ,
#90000
b1001 !
b1001 0
b1001 L
b1001 1
b1001 @
b1001 I
b1001 K
b1001 )
b1001 '
b1001 %
b1001 $
b1001 /
b1001 E
b1001 H
b1010 -
b1001 ,
#100000
b1010 !
b1010 0
b1010 L
b1010 1
b1010 @
b1010 I
b1010 K
b1010 )
b1010 '
b1010 %
b1010 $
b1010 /
b1010 E
b1010 H
b1011 -
b1010 ,
#110000
b1011 !
b1011 0
b1011 L
b1011 1
b1011 @
b1011 I
b1011 K
b1011 )
b1011 '
b1011 %
b1011 $
b1011 /
b1011 E
b1011 H
b1100 -
b1011 ,
#120000
b1100 !
b1100 0
b1100 L
b1100 1
b1100 @
b1100 I
b1100 K
b1100 )
b1100 '
b1100 %
b1100 $
b1100 /
b1100 E
b1100 H
b1101 -
b1100 ,
#130000
b1101 !
b1101 0
b1101 L
b1101 1
b1101 @
b1101 I
b1101 K
b1101 )
b1101 '
b1101 %
b1101 $
b1101 /
b1101 E
b1101 H
b1110 -
b1101 ,
#140000
b1110 !
b1110 0
b1110 L
b1110 1
b1110 @
b1110 I
b1110 K
b1110 )
b1110 '
b1110 %
b1110 $
b1110 /
b1110 E
b1110 H
b1111 -
b1110 ,
#150000
b1111 !
b1111 0
b1111 L
b1111 1
b1111 @
b1111 I
b1111 K
b1111 )
b1111 '
b1111 %
b1111 $
b1111 /
b1111 E
b1111 H
b10000 -
b1111 ,
#160000
b10000 !
b10000 0
b10000 L
b10000 1
b10000 @
b10000 I
b10000 K
b10000 )
b10000 '
b10000 %
b10000 $
b10000 /
b10000 E
b10000 H
b10001 -
b10000 ,
#170000
b10001 !
b10001 0
b10001 L
b10001 1
b10001 @
b10001 I
b10001 K
b10001 )
b10001 '
b10001 %
b10001 $
b10001 /
b10001 E
b10001 H
b10010 -
b10001 ,
#180000
b10010 !
b10010 0
b10010 L
b10010 1
b10010 @
b10010 I
b10010 K
b10010 )
b10010 '
b10010 %
b10010 $
b10010 /
b10010 E
b10010 H
b10011 -
b10010 ,
#190000
b10011 !
b10011 0
b10011 L
b10011 1
b10011 @
b10011 I
b10011 K
b10011 )
b10011 '
b10011 %
b10011 $
b10011 /
b10011 E
b10011 H
b10100 -
b10011 ,
#200000
b10100 !
b10100 0
b10100 L
b10100 1
b10100 @
b10100 I
b10100 K
b10100 )
b10100 '
b10100 %
b10100 $
b10100 /
b10100 E
b10100 H
b10101 -
b10100 ,
#210000
b10101 !
b10101 0
b10101 L
b10101 1
b10101 @
b10101 I
b10101 K
b10101 )
b10101 '
b10101 %
b10101 $
b10101 /
b10101 E
b10101 H
b10110 -
b10101 ,
#220000
b10110 !
b10110 0
b10110 L
b10110 1
b10110 @
b10110 I
b10110 K
b10110 )
b10110 '
b10110 %
b10110 $
b10110 /
b10110 E
b10110 H
b10111 -
b10110 ,
#230000
b10111 !
b10111 0
b10111 L
b10111 1
b10111 @
b10111 I
b10111 K
b10111 )
b10111 '
b10111 %
b10111 $
b10111 /
b10111 E
b10111 H
b11000 -
b10111 ,
#240000
b11000 !
b11000 0
b11000 L
b11000 1
b11000 @
b11000 I
b11000 K
b11000 )
b11000 '
b11000 %
b11000 $
b11000 /
b11000 E
b11000 H
b11001 -
b11000 ,
#250000
b11001 !
b11001 0
b11001 L
b11001 1
b11001 @
b11001 I
b11001 K
b11001 )
b11001 '
b11001 %
b11001 $
b11001 /
b11001 E
b11001 H
b11010 -
b11001 ,
#260000
b11010 !
b11010 0
b11010 L
b11010 1
b11010 @
b11010 I
b11010 K
b11010 )
b11010 '
b11010 %
b11010 $
b11010 /
b11010 E
b11010 H
b11011 -
b11010 ,
#270000
b11011 !
b11011 0
b11011 L
b11011 1
b11011 @
b11011 I
b11011 K
b11011 )
b11011 '
b11011 %
b11011 $
b11011 /
b11011 E
b11011 H
b11100 -
b11011 ,
#280000
b11100 !
b11100 0
b11100 L
b11100 1
b11100 @
b11100 I
b11100 K
b11100 )
b11100 '
b11100 %
b11100 $
b11100 /
b11100 E
b11100 H
b11101 -
b11100 ,
#290000
b11101 !
b11101 0
b11101 L
b11101 1
b11101 @
b11101 I
b11101 K
b11101 )
b11101 '
b11101 %
b11101 $
b11101 /
b11101 E
b11101 H
b11110 -
b11101 ,
#300000
b11110 !
b11110 0
b11110 L
b11110 1
b11110 @
b11110 I
b11110 K
b11110 )
b11110 '
b11110 %
b11110 $
b11110 /
b11110 E
b11110 H
b11111 -
b11110 ,
#310000
b11111 !
b11111 0
b11111 L
b11111 1
b11111 @
b11111 I
b11111 K
b11111 )
b11111 '
b11111 %
b11111 $
b11111 /
b11111 E
b11111 H
b100000 -
b11111 ,
#320000
b1 !
b1 0
b1 L
b1 1
b1 @
b1 I
b1 K
b1 )
b1 '
b1 %
b0 $
b0 /
b0 E
b0 H
b1 #
b1 .
b1 D
b1 G
b100001 -
b1 +
b0 ,
#330000
b10 4
b10 J
b1 3
b1 C
b1 B
b10 !
b10 0
b10 L
b11110 2
b11110 A
b11110 F
b0 1
b0 @
b0 I
b0 K
b10 )
b10 '
b10 %
b1 $
b1 /
b1 E
b1 H
b100010 -
b1 ,
#340000
b0 4
b0 J
b0 3
b0 C
b0 B
16
b11 !
b11 0
b11 L
b11111 2
b11111 A
b11111 F
b11 1
b11 @
b11 I
b11 K
b11 )
b11 '
b11 %
b10 $
b10 /
b10 E
b10 H
b100011 -
b10 ,
#350000
06
b110 4
b110 J
b11 3
b11 C
b1 B
b100 !
b100 0
b100 L
b11110 2
b11110 A
b11110 F
b10 1
b10 @
b10 I
b10 K
b100 )
b100 '
b100 %
b11 $
b11 /
b11 E
b11 H
b100100 -
b11 ,
#360000
b0 4
b0 J
b0 3
b0 C
b0 B
16
b101 !
b101 0
b101 L
b11111 2
b11111 A
b11111 F
b101 1
b101 @
b101 I
b101 K
b101 )
b101 '
b101 %
b100 $
b100 /
b100 E
b100 H
b100101 -
b100 ,
#370000
b10 4
b10 J
b1 3
b1 C
b1 B
b110 !
b110 0
b110 L
b11110 2
b11110 A
b11110 F
b100 1
b100 @
b100 I
b100 K
b110 )
b110 '
b110 %
b101 $
b101 /
b101 E
b101 H
b100110 -
b101 ,
#380000
b0 4
b0 J
b0 3
b0 C
18
b0 B
16
b111 !
b111 0
b111 L
b11111 2
b11111 A
b11111 F
b111 1
b111 @
b111 I
b111 K
b111 )
b111 '
b111 %
b110 $
b110 /
b110 E
b110 H
b100111 -
b110 ,
#390000
06
08
b1110 4
b1110 J
b111 3
b111 C
b1 B
b1000 !
b1000 0
b1000 L
b11110 2
b11110 A
b11110 F
b110 1
b110 @
b110 I
b110 K
b1000 )
b1000 '
b1000 %
b111 $
b111 /
b111 E
b111 H
b101000 -
b111 ,
#400000
b0 4
b0 J
b0 3
b0 C
18
b0 B
16
b1001 !
b1001 0
b1001 L
b11111 2
b11111 A
b11111 F
b1001 1
b1001 @
b1001 I
b1001 K
b1001 )
b1001 '
b1001 %
b1000 $
b1000 /
b1000 E
b1000 H
b101001 -
b1000 ,
#410000
b10 4
b10 J
b1 3
b1 C
b1 B
b1010 !
b1010 0
b1010 L
b11110 2
b11110 A
b11110 F
b1000 1
b1000 @
b1000 I
b1000 K
b1010 )
b1010 '
b1010 %
b1001 $
b1001 /
b1001 E
b1001 H
b101010 -
b1001 ,
#420000
b0 4
b0 J
b0 3
b0 C
b0 B
16
b1011 !
b1011 0
b1011 L
b11111 2
b11111 A
b11111 F
b1011 1
b1011 @
b1011 I
b1011 K
b1011 )
b1011 '
b1011 %
b1010 $
b1010 /
b1010 E
b1010 H
b101011 -
b1010 ,
#430000
06
b110 4
b110 J
b11 3
b11 C
b1 B
b1100 !
b1100 0
b1100 L
b11110 2
b11110 A
b11110 F
b1010 1
b1010 @
b1010 I
b1010 K
b1100 )
b1100 '
b1100 %
b1011 $
b1011 /
b1011 E
b1011 H
b101100 -
b1011 ,
#440000
b0 4
b0 J
b0 3
b0 C
b0 B
16
b1101 !
b1101 0
b1101 L
b11111 2
b11111 A
b11111 F
b1101 1
b1101 @
b1101 I
b1101 K
b1101 )
b1101 '
b1101 %
b1100 $
b1100 /
b1100 E
b1100 H
b101101 -
b1100 ,
#450000
b10 4
b10 J
b1 3
b1 C
b1 B
b1110 !
b1110 0
b1110 L
b11110 2
b11110 A
b11110 F
b1100 1
b1100 @
b1100 I
b1100 K
b1110 )
b1110 '
b1110 %
b1101 $
b1101 /
b1101 E
b1101 H
b101110 -
b1101 ,
#460000
b0 4
b0 J
b0 3
b0 C
1;
18
b0 B
16
b1111 !
b1111 0
b1111 L
b11111 2
b11111 A
b11111 F
b1111 1
b1111 @
b1111 I
b1111 K
b1111 )
b1111 '
b1111 %
b1110 $
b1110 /
b1110 E
b1110 H
b101111 -
b1110 ,
#470000
06
08
0;
b11110 4
b11110 J
b1111 3
b1111 C
b1 B
b10000 !
b10000 0
b10000 L
b11110 2
b11110 A
b11110 F
b1110 1
b1110 @
b1110 I
b1110 K
b10000 )
b10000 '
b10000 %
b1111 $
b1111 /
b1111 E
b1111 H
b110000 -
b1111 ,
#480000
b0 4
b0 J
b0 3
b0 C
1;
18
b0 B
16
b10001 !
b10001 0
b10001 L
b11111 2
b11111 A
b11111 F
b10001 1
b10001 @
b10001 I
b10001 K
b10001 )
b10001 '
b10001 %
b10000 $
b10000 /
b10000 E
b10000 H
b110001 -
b10000 ,
#490000
b10 4
b10 J
b1 3
b1 C
b1 B
b10010 !
b10010 0
b10010 L
b11110 2
b11110 A
b11110 F
b10000 1
b10000 @
b10000 I
b10000 K
b10010 )
b10010 '
b10010 %
b10001 $
b10001 /
b10001 E
b10001 H
b110010 -
b10001 ,
#500000
b0 4
b0 J
b0 3
b0 C
b0 B
16
b10011 !
b10011 0
b10011 L
b11111 2
b11111 A
b11111 F
b10011 1
b10011 @
b10011 I
b10011 K
b10011 )
b10011 '
b10011 %
b10010 $
b10010 /
b10010 E
b10010 H
b110011 -
b10010 ,
#510000
06
b110 4
b110 J
b11 3
b11 C
b1 B
b10100 !
b10100 0
b10100 L
b11110 2
b11110 A
b11110 F
b10010 1
b10010 @
b10010 I
b10010 K
b10100 )
b10100 '
b10100 %
b10011 $
b10011 /
b10011 E
b10011 H
b110100 -
b10011 ,
#520000
b0 4
b0 J
b0 3
b0 C
b0 B
16
b10101 !
b10101 0
b10101 L
b11111 2
b11111 A
b11111 F
b10101 1
b10101 @
b10101 I
b10101 K
b10101 )
b10101 '
b10101 %
b10100 $
b10100 /
b10100 E
b10100 H
b110101 -
b10100 ,
#530000
b10 4
b10 J
b1 3
b1 C
b1 B
b10110 !
b10110 0
b10110 L
b11110 2
b11110 A
b11110 F
b10100 1
b10100 @
b10100 I
b10100 K
b10110 )
b10110 '
b10110 %
b10101 $
b10101 /
b10101 E
b10101 H
b110110 -
b10101 ,
#540000
b0 4
b0 J
b0 3
b0 C
18
b0 B
16
b10111 !
b10111 0
b10111 L
b11111 2
b11111 A
b11111 F
b10111 1
b10111 @
b10111 I
b10111 K
b10111 )
b10111 '
b10111 %
b10110 $
b10110 /
b10110 E
b10110 H
b110111 -
b10110 ,
#550000
06
08
b1110 4
b1110 J
b111 3
b111 C
b1 B
b11000 !
b11000 0
b11000 L
b11110 2
b11110 A
b11110 F
b10110 1
b10110 @
b10110 I
b10110 K
b11000 )
b11000 '
b11000 %
b10111 $
b10111 /
b10111 E
b10111 H
b111000 -
b10111 ,
#560000
b0 4
b0 J
b0 3
b0 C
18
b0 B
16
b11001 !
b11001 0
b11001 L
b11111 2
b11111 A
b11111 F
b11001 1
b11001 @
b11001 I
b11001 K
b11001 )
b11001 '
b11001 %
b11000 $
b11000 /
b11000 E
b11000 H
b111001 -
b11000 ,
#570000
b10 4
b10 J
b1 3
b1 C
b1 B
b11010 !
b11010 0
b11010 L
b11110 2
b11110 A
b11110 F
b11000 1
b11000 @
b11000 I
b11000 K
b11010 )
b11010 '
b11010 %
b11001 $
b11001 /
b11001 E
b11001 H
b111010 -
b11001 ,
#580000
b0 4
b0 J
b0 3
b0 C
b0 B
16
b11011 !
b11011 0
b11011 L
b11111 2
b11111 A
b11111 F
b11011 1
b11011 @
b11011 I
b11011 K
b11011 )
b11011 '
b11011 %
b11010 $
b11010 /
b11010 E
b11010 H
b111011 -
b11010 ,
#590000
06
b110 4
b110 J
b11 3
b11 C
b1 B
b11100 !
b11100 0
b11100 L
b11110 2
b11110 A
b11110 F
b11010 1
b11010 @
b11010 I
b11010 K
b11100 )
b11100 '
b11100 %
b11011 $
b11011 /
b11011 E
b11011 H
b111100 -
b11011 ,
#600000
b0 4
b0 J
b0 3
b0 C
b0 B
16
b11101 !
b11101 0
b11101 L
b11111 2
b11111 A
b11111 F
b11101 1
b11101 @
b11101 I
b11101 K
b11101 )
b11101 '
b11101 %
b11100 $
b11100 /
b11100 E
b11100 H
b111101 -
b11100 ,
#610000
b10 4
b10 J
b1 3
b1 C
b1 B
b11110 !
b11110 0
b11110 L
b11110 2
b11110 A
b11110 F
b11100 1
b11100 @
b11100 I
b11100 K
b11110 )
b11110 '
b11110 %
b11101 $
b11101 /
b11101 E
b11101 H
b111110 -
b11101 ,
#620000
0"
b0 4
b0 J
b0 3
b0 C
1?
1;
18
b0 B
16
b11111 !
b11111 0
b11111 L
b11111 2
b11111 A
b11111 F
b11111 1
b11111 @
b11111 I
b11111 K
b11111 )
b11111 '
b11111 %
b11110 $
b11110 /
b11110 E
b11110 H
b111111 -
b11110 ,
#630000
1"
06
08
0;
0?
b11110 4
b11110 J
b11111 3
b11111 C
b1 B
b0 !
b0 0
b0 L
b11110 2
b11110 A
b11110 F
b11110 1
b11110 @
b11110 I
b11110 K
1(
b0 )
b100000 '
b100000 %
b11111 $
b11111 /
b11111 E
b11111 H
b1000000 -
b11111 ,
#640000
0"
16
1?
1;
b0 4
b0 J
18
b0 3
b0 C
b0 B
b10 !
b10 0
b10 L
b11111 2
b11111 A
b11111 F
b10 1
b10 @
b10 I
b10 K
0(
b10 )
b10 '
b10 %
b0 $
b0 /
b0 E
b0 H
b10 #
b10 .
b10 D
b10 G
b1000001 -
b10 +
b0 ,
#650000
b11 !
b11 0
b11 L
b11 1
b11 @
b11 I
b11 K
b11 )
b11 '
b11 %
b1 $
b1 /
b1 E
b1 H
b1000010 -
b1 ,
#660000
b100 4
b100 J
b10 3
b10 C
b10 B
b100 !
b100 0
b100 L
b11101 2
b11101 A
b11101 F
b0 1
b0 @
b0 I
b0 K
b100 )
b100 '
b100 %
b10 $
b10 /
b10 E
b10 H
b1000011 -
b10 ,
#670000
b101 !
b101 0
b101 L
b1 1
b1 @
b1 I
b1 K
b101 )
b101 '
b101 %
b11 $
b11 /
b11 E
b11 H
b1000100 -
b11 ,
#680000
b0 4
b0 J
b0 3
b0 C
b0 B
17
b110 !
b110 0
b110 L
b11111 2
b11111 A
b11111 F
b110 1
b110 @
b110 I
b110 K
b110 )
b110 '
b110 %
b100 $
b100 /
b100 E
b100 H
b1000101 -
b100 ,
#690000
b111 !
b111 0
b111 L
b111 1
b111 @
b111 I
b111 K
b111 )
b111 '
b111 %
b101 $
b101 /
b101 E
b101 H
b1000110 -
b101 ,
#700000
b1100 4
b1100 J
07
b110 3
b110 C
b10 B
b1000 !
b1000 0
b1000 L
b11101 2
b11101 A
b11101 F
b100 1
b100 @
b100 I
b100 K
b1000 )
b1000 '
b1000 %
b110 $
b110 /
b110 E
b110 H
b1000111 -
b110 ,
#710000
b1001 !
b1001 0
b1001 L
b101 1
b101 @
b101 I
b101 K
b1001 )
b1001 '
b1001 %
b111 $
b111 /
b111 E
b111 H
b1001000 -
b111 ,
#720000
b0 4
b0 J
b0 3
b0 C
b0 B
17
b1010 !
b1010 0
b1010 L
b11111 2
b11111 A
b11111 F
b1010 1
b1010 @
b1010 I
b1010 K
b1010 )
b1010 '
b1010 %
b1000 $
b1000 /
b1000 E
b1000 H
b1001001 -
b1000 ,
#730000
b1011 !
b1011 0
b1011 L
b1011 1
b1011 @
b1011 I
b1011 K
b1011 )
b1011 '
b1011 %
b1001 $
b1001 /
b1001 E
b1001 H
b1001010 -
b1001 ,
#740000
b100 4
b100 J
b10 3
b10 C
b10 B
b1100 !
b1100 0
b1100 L
b11101 2
b11101 A
b11101 F
b1000 1
b1000 @
b1000 I
b1000 K
b1100 )
b1100 '
b1100 %
b1010 $
b1010 /
b1010 E
b1010 H
b1001011 -
b1010 ,
#750000
b1101 !
b1101 0
b1101 L
b1001 1
b1001 @
b1001 I
b1001 K
b1101 )
b1101 '
b1101 %
b1011 $
b1011 /
b1011 E
b1011 H
b1001100 -
b1011 ,
#760000
b0 4
b0 J
b0 3
b0 C
1:
b0 B
17
b1110 !
b1110 0
b1110 L
b11111 2
b11111 A
b11111 F
b1110 1
b1110 @
b1110 I
b1110 K
b1110 )
b1110 '
b1110 %
b1100 $
b1100 /
b1100 E
b1100 H
b1001101 -
b1100 ,
#770000
b1111 !
b1111 0
b1111 L
b1111 1
b1111 @
b1111 I
b1111 K
b1111 )
b1111 '
b1111 %
b1101 $
b1101 /
b1101 E
b1101 H
b1001110 -
b1101 ,
